example_package_amsvenkat/__init__.py
example_package_amsvenkat/example.py
example_package_amsvenkat-0.0.1.dist-info/licenses/LICENSE
example_package_amsvenkat-0.0.1.dist-info/METADATA
example_package_amsvenkat-0.0.1.dist-info/WHEEL
example_package_amsvenkat-0.0.1.dist-info/top_level.txt
example_package_amsvenkat-0.0.1.dist-info/RECORD
