Metadata-Version: 2.4
Name: example_package_amsvenkat
Version: 0.0.1
Summary: A small example package
Author-email: Example Author <amrutha.venkatesan@telekinesis.ai>
License-Expression: MIT
Project-URL: Homepage, https://telekinesis.ai
Project-URL: Issues, https://github.com/telekinesis-ai/telekinesis-examples/issues
Classifier: Programming Language :: Python :: 3
Classifier: Operating System :: OS Independent
Requires-Python: >=3.11
License-File: LICENSE
Dynamic: license-file
